[{"type":"Point","gid":2,"name":"Vieng Joom On","fsq_id":"4b6bc210f964a52091172ce3","chkins":13,"people":null,"coords":[18.792487950193,99.001759155604],"weight":null},{"type":"Point","gid":35,"name":"The Salad Concept","fsq_id":"4c73348313228cfaa1512d65","chkins":24,"people":null,"coords":[18.796377219768,98.966265101608],"weight":null},{"type":"Point","gid":36,"name":"Luvv Coffee","fsq_id":"4c260d5ef7ced13abd8e256d","chkins":10,"people":null,"coords":[18.7958147095,98.96559662871],"weight":null},{"type":"Point","gid":37,"name":"Cafe De Nimman","fsq_id":"4ba8bd2cf964a52012eb39e3","chkins":13,"people":null,"coords":[18.79338886244,98.972095670771],"weight":null},{"type":"Point","gid":38,"name":"iBerry Garden","fsq_id":"4d16ee726c8b54814b1be7cc","chkins":67,"people":null,"coords":[18.794302953842,98.968567619366],"weight":null},{"type":"Point","gid":39,"name":"Khun Mor's Cuisine","fsq_id":"4b908806f964a520c38e33e3","chkins":7,"people":null,"coords":[18.795111569022,98.967044986655],"weight":null},{"type":"Point","gid":40,"name":"Myeong-dong Korean BBQ","fsq_id":"5122126ae4b0841ef27f31eb","chkins":14,"people":null,"coords":[18.801404571809,98.982716962367],"weight":null},{"type":"Point","gid":41,"name":"Must Taste Suki & Shabu","fsq_id":"4e3ea399aeb73139a18899c8","chkins":1,"people":null,"coords":[18.798908492712,98.979745971711],"weight":null},{"type":"Point","gid":42,"name":"Guu Fusion Roti & Tea","fsq_id":"4c13727c82a3c9b64672fbf8","chkins":26,"people":null,"coords":[18.799154586657,98.967193536188],"weight":null},{"type":"Point","gid":43,"name":"Best Taste Kitchen","fsq_id":"4bcab49e68f976b082f55f83","chkins":7,"people":null,"coords":[18.796799101235,98.968196245534],"weight":null},{"type":"Point","gid":44,"name":"Kua-Kai Nimman","fsq_id":"4e771e37ae60c32851d8d8d8","chkins":56,"people":null,"coords":[18.794338111105,98.968976130582],"weight":null},{"type":"Point","gid":45,"name":"Ristr8to2","fsq_id":"4df88002d164d347cc72a67b","chkins":33,"people":null,"coords":[18.799009567053,98.967156398805],"weight":null},{"type":"Point","gid":46,"name":"Cherng Doi Roast Chicken","fsq_id":"4e1e80bc2271ad66e4a07e80","chkins":5,"people":null,"coords":[18.799418258352,98.965986571234],"weight":null},{"type":"Point","gid":47,"name":"Milk Garden","fsq_id":"4c95c53b533aa093a04bcc45","chkins":18,"people":null,"coords":[18.797875773732,98.962551363288],"weight":null},{"type":"Point","gid":48,"name":"Itth The Ribs Noodle","fsq_id":"4d4fd5fd71548cfa33ef089a","chkins":2,"people":null,"coords":[18.805680339587,98.959413254407],"weight":null},{"type":"Point","gid":49,"name":"Penguin Ghetto","fsq_id":"50a5ee0ae4b0d40bc23bfa62","chkins":5,"people":null,"coords":[18.80998675845,98.962551363288],"weight":null},{"type":"Point","gid":50,"name":"Hmon-Oon","fsq_id":"4dfeffb2a809baedbd902e3e","chkins":2,"people":null,"coords":[18.807965391895,98.95701789319],"weight":null},{"type":"Point","gid":51,"name":"Boat","fsq_id":"4bb6a1aaef159c741f4f76f7","chkins":15,"people":null,"coords":[18.807051374696,98.956962187115],"weight":null},{"type":"Point","gid":52,"name":"Milk Zone","fsq_id":"4bc9d8193740b71348585f65","chkins":8,"people":null,"coords":[18.80692833354,98.957259286181],"weight":null},{"type":"Point","gid":53,"name":"Mo'C Mo'L","fsq_id":"4c0b9c1d340720a162538893","chkins":7,"people":null,"coords":[18.806699828297,98.957556385247],"weight":null},{"type":"Point","gid":54,"name":"Tsunami","fsq_id":"4bf1481821072d7f2fbd208b","chkins":21,"people":null,"coords":[18.806260394266,98.959264704874],"weight":null},{"type":"Point","gid":55,"name":"Ponyangkam","fsq_id":"4c14be077f7f2d7f7452e168","chkins":5,"people":null,"coords":[18.80270972519,98.95933897964],"weight":null},{"type":"Point","gid":56,"name":"2nd Arch Moo Jum","fsq_id":"4ba60c02f964a520113039e3","chkins":2,"people":null,"coords":[18.799299606143,98.961362967025],"weight":null},{"type":"Point","gid":57,"name":"PAPER SPooN","fsq_id":"4cf0828dcc61a35d1b640f9e","chkins":4,"people":null,"coords":[18.780785271476,98.952789517252],"weight":null},{"type":"Point","gid":58,"name":"Banana Tree","fsq_id":"4d0f51d3d21db60c64712318","chkins":7,"people":null,"coords":[18.77825636317,98.953700121668],"weight":null},{"type":"Point","gid":59,"name":"Sibsongpanna Khantoke","fsq_id":"4d5bcc37fb186dcb45b7f79a","chkins":0,"people":null,"coords":[18.78426245842,98.956310520994],"weight":null},{"type":"Point","gid":60,"name":"Kin Sen","fsq_id":"4fd5f4a7e4b0296d1f7f4b5f","chkins":12,"people":null,"coords":[18.78334287877,98.957615720657],"weight":null},{"type":"Point","gid":61,"name":"Happy in Garden","fsq_id":"4bdd03874ffaa59378a36ef7","chkins":5,"people":null,"coords":[18.788917753358,98.959588696891],"weight":null},{"type":"Point","gid":62,"name":"At Chiang Mai","fsq_id":"4d0dd278f393224b85b61eee","chkins":0,"people":null,"coords":[18.792164889078,98.95555168398],"weight":null},{"type":"Point","gid":63,"name":"Kasem Fastfood","fsq_id":"4e4c929fb61c258863275de1","chkins":15,"people":null,"coords":[18.78805567141,98.95722112541],"weight":null},{"type":"Point","gid":64,"name":"Tu Kub Kao","fsq_id":"4c9efee919e4236af7445589","chkins":0,"people":null,"coords":[18.788745337322,98.955096381772],"weight":null},{"type":"Point","gid":65,"name":"Nong Ploy Fastfood","fsq_id":"4e30f5d41495f249f7674a97","chkins":0,"people":null,"coords":[18.79291200879,98.952728810291],"weight":null},{"type":"Point","gid":66,"name":"I Like Ice Cream","fsq_id":"4c7f538cfb74236a05daf9b9","chkins":26,"people":null,"coords":[18.79285453816,98.954216130837],"weight":null},{"type":"Point","gid":67,"name":"Aj. Bella","fsq_id":"4c98a04ef419a09383f27088","chkins":7,"people":null,"coords":[18.792682126155,98.954914260889],"weight":null},{"type":"Point","gid":68,"name":"Diew Nom Sod","fsq_id":"4df45ccb483bdb5e1377aed2","chkins":5,"people":null,"coords":[18.793199361642,98.953153759018],"weight":null},{"type":"Point","gid":69,"name":"Tee Noi","fsq_id":"4d031c2c2f96f04d27121654","chkins":15,"people":null,"coords":[18.793343037885,98.952728810291],"weight":null},{"type":"Point","gid":70,"name":"Supattra's Cottage","fsq_id":"4c2dccda1683b713566f26ec","chkins":5,"people":null,"coords":[18.794090152369,98.949966643562],"weight":null},{"type":"Point","gid":71,"name":"Galae","fsq_id":"4d205993dd6a236adfc83638","chkins":13,"people":null,"coords":[18.793371773118,98.945474328443],"weight":null},{"type":"Point","gid":72,"name":"Palaad Tawanron","fsq_id":"4be7efde88ed2d7f1a37cb1d","chkins":5,"people":null,"coords":[18.801302510146,98.942347919949],"weight":null},{"type":"Point","gid":73,"name":"CoffiZebra","fsq_id":"4c1dfdcdeac020a1d40449c2","chkins":0,"people":null,"coords":[18.788917753358,98.97036418248],"weight":null},{"type":"Point","gid":74,"name":"Jipata Resturant","fsq_id":"4c7a648abd346dcb3647f8ef","chkins":2,"people":null,"coords":[18.785929183739,98.970546303364],"weight":null},{"type":"Point","gid":75,"name":"Crazy Noodle","fsq_id":"522d911911d22b5c2fe57901","chkins":15,"people":null,"coords":[18.786360230707,98.970546303364],"weight":null},{"type":"Point","gid":76,"name":"Kuang Rad Nar","fsq_id":"4c0f7ad41281c9b6ef911e1d","chkins":0,"people":null,"coords":[18.789176377082,98.967237773986],"weight":null},{"type":"Point","gid":77,"name":"Kao Tom Yong","fsq_id":"4b964e40f964a52010c534e3","chkins":9,"people":null,"coords":[18.789808566735,98.963716770244],"weight":null},{"type":"Point","gid":78,"name":"Lum Him Khue","fsq_id":"4edcc27f46907c1b456a3646","chkins":12,"people":null,"coords":[18.786216548507,98.978347147861],"weight":null},{"type":"Point","gid":79,"name":"Monkey's Kitchen","fsq_id":"506ee205e4b05bc762cbd8c1","chkins":7,"people":null,"coords":[18.787653364991,98.962988286711],"weight":null},{"type":"Point","gid":80,"name":"Mei Jieng","fsq_id":"4c9b3f41eaa5a14370ead2e4","chkins":6,"people":null,"coords":[18.765007712089,98.993827422932],"weight":null},{"type":"Point","gid":81,"name":"Baan Bekery","fsq_id":"4c735c1c376da0931dfda8c6","chkins":6,"people":null,"coords":[18.779405871651,98.98854591732],"weight":null},{"type":"Point","gid":82,"name":"Flight Control Tower Restaurant","fsq_id":"4cdce2923f6a8cfa8a94f4ea","chkins":1,"people":null,"coords":[18.769663538932,98.970515949883],"weight":null},{"type":"Point","gid":83,"name":"Susu Run","fsq_id":"4cb1a6631463a143ca11a7a9","chkins":2,"people":null,"coords":[18.767651777674,98.980896840225],"weight":null},{"type":"Point","gid":84,"name":"Khun Churn","fsq_id":"4cef9cff7b9437046fcd3353","chkins":10,"people":null,"coords":[18.772451225567,98.980107649731],"weight":null},{"type":"Point","gid":85,"name":"Rimping Ancient House","fsq_id":"4be5630c910020a138dfd214","chkins":3,"people":null,"coords":[18.777825295468,99.007425782211],"weight":null},{"type":"Point","gid":86,"name":"Tengoku de Cuisine","fsq_id":"4c011a3f19d8c92852428829","chkins":14,"people":null,"coords":[18.778299469857,99.039615648316],"weight":null},{"type":"Point","gid":87,"name":"Khum Khan Tok","fsq_id":"4ba374d7f964a520963e38e3","chkins":14,"people":null,"coords":[18.799664671159,99.026093172739],"weight":null},{"type":"Point","gid":88,"name":"I Din Klin Krok","fsq_id":"4c9893e007916dcb5bf9ec1b","chkins":4,"people":null,"coords":[18.798429097867,99.023968429101],"weight":null},{"type":"Point","gid":89,"name":"Bee Hiang","fsq_id":"4d43a0754e5d37049e02e293","chkins":7,"people":null,"coords":[18.791503972724,99.027094837596],"weight":null},{"type":"Point","gid":90,"name":"Lumdee Te Khuadang","fsq_id":"516548aee4b02da86110629f","chkins":7,"people":null,"coords":[18.798457832232,99.033226240664],"weight":null},{"type":"Point","gid":91,"name":"Mai Bakery in Garden","fsq_id":"4bc940e9fb84c9b6e8e71a3e","chkins":9,"people":null,"coords":[18.810973407585,98.989152807959],"weight":null},{"type":"Point","gid":92,"name":"Salad Terrace","fsq_id":"4f016d0830f8992333ba34d7","chkins":9,"people":null,"coords":[18.803272403373,98.987696673922],"weight":null},{"type":"Point","gid":93,"name":"Leela Noodle","fsq_id":"4d7f539687003704efde8199","chkins":5,"people":null,"coords":[18.804890542459,98.986715366202],"weight":null},{"type":"Point","gid":94,"name":"Mama Fha Thani","fsq_id":"4cd04ab51ac7a1cddfab1892","chkins":6,"people":null,"coords":[18.803624499777,98.97606342917],"weight":null},{"type":"Point","gid":95,"name":"Somtum Priow Pak","fsq_id":"4e620a78483bd9a9742361fa","chkins":3,"people":null,"coords":[18.80506284339,98.97691811654],"weight":null},{"type":"Point","gid":96,"name":"Somtum Udorn","fsq_id":"4bd52e2dcfa7b713b38125da","chkins":41,"people":null,"coords":[18.806980615747,98.976443290223],"weight":null},{"type":"Point","gid":97,"name":"Baan Ched Yod","fsq_id":"4b95d911f964a5207cb534e3","chkins":12,"people":null,"coords":[18.809677446139,98.974385709519],"weight":null},{"type":"Point","gid":98,"name":"Kao Soi Lamduan Fa Ham 2","fsq_id":"4b8c9b37f964a52007d832e3","chkins":9,"people":null,"coords":[18.811625130089,98.978564181103],"weight":null},{"type":"Point","gid":99,"name":"Pure Ocha","fsq_id":"4bb0919cf964a5207e4c3ce3","chkins":0,"people":null,"coords":[18.812793729632,98.965174078981],"weight":null},{"type":"Point","gid":100,"name":"Pattalung Southern Food","fsq_id":"4cd25586df88a35d008868a0","chkins":3,"people":null,"coords":[18.811804915162,98.963622979681],"weight":null},{"type":"Point","gid":101,"name":"Kang Ron Baan Suan","fsq_id":"4b8a600ef964a520796a32e3","chkins":10,"people":null,"coords":[18.82071901737,98.961945260029],"weight":null},{"type":"Point","gid":102,"name":"Kaotom Pathom","fsq_id":"4c3e7695ca012d7fe69e2fbe","chkins":2,"people":null,"coords":[18.807497511588,98.984689440585],"weight":null},{"type":"Point","gid":103,"name":"Instant Steak","fsq_id":"4cb6a1d2b315a093fc829d76","chkins":1,"people":null,"coords":[18.799354344748,99.010994818513],"weight":null},{"type":"Point","gid":104,"name":"Rad Nar Near McCormick","fsq_id":"4bea33a6b3352d7fcffb54d2","chkins":5,"people":null,"coords":[18.79752638562,99.009032203072],"weight":null},{"type":"Point","gid":105,"name":"3 Baht Noodle","fsq_id":"4e2a3d6aae605c533a2b2931","chkins":15,"people":null,"coords":[18.801624282753,99.00934875395],"weight":null},{"type":"Point","gid":106,"name":"Kao Soi Lamduan Fa Ham","fsq_id":"4bdfb9980ee3a593d24035b0","chkins":11,"people":null,"coords":[18.801834044456,99.005645108682],"weight":null},{"type":"Point","gid":107,"name":"Somtum Luang Prabang","fsq_id":"4e6b676daeb7c31e43793525","chkins":5,"people":null,"coords":[18.814074685189,99.000532812009],"weight":null},{"type":"Point","gid":108,"name":"Baan Rai Yarm Yen","fsq_id":"4bb4ab2386a8d13a1aafde7f","chkins":9,"people":null,"coords":[18.812703837648,99.007591896579],"weight":null},{"type":"Point","gid":109,"name":"Jia Tong Heng","fsq_id":"4e210fe41f6effe84f6de2e5","chkins":16,"people":null,"coords":[18.809647481594,99.013036571674],"weight":null},{"type":"Point","gid":110,"name":"Great Tease of the Seven Sea","fsq_id":"509354dfe4b0f71701bfdbdf","chkins":11,"people":null,"coords":[18.820883811449,99.016613596591],"weight":null},{"type":"Point","gid":111,"name":"NON'Z","fsq_id":"4be2b60821d5a5936c121711","chkins":7,"people":null,"coords":[18.82708594386,99.012688365709],"weight":null},{"type":"Point","gid":112,"name":"3rd Arch Moo Jum","fsq_id":"4d5133c2bd6ff04dbd21ef0c","chkins":3,"people":null,"coords":[18.800148451954,99.013321467464],"weight":null},{"type":"Point","gid":113,"name":"Somtum Udorn","fsq_id":"52b3e08c498e1f5ec7dc6d7b","chkins":11,"people":null,"coords":[18.781995424088,99.030494352574],"weight":null},{"type":"Point","gid":114,"name":"Dhara Dhevi Cake Shop","fsq_id":"5203426f498e94f1a2852c25","chkins":50,"people":null,"coords":[18.778339109127,99.039009571181],"weight":null},{"type":"Point","gid":115,"name":"Nutthakarn Kitchen","fsq_id":"4c73c7f3d944224b021e1029","chkins":0,"people":null,"coords":[18.783988382028,99.021820858528],"weight":null},{"type":"Point","gid":116,"name":"Tongta&Tawan Bakery","fsq_id":"4c458a0ff799e21e9f46afa2","chkins":1,"people":null,"coords":[18.764327495715,98.991495284453],"weight":null},{"type":"Point","gid":117,"name":"Phet Doi Ngam","fsq_id":"4bc31952920eb713e5ee1c2c","chkins":4,"people":null,"coords":[18.762529129467,98.995293894984],"weight":null},{"type":"Point","gid":118,"name":"Baan Rim Nam","fsq_id":"4da43ace22a5f04df48e3355","chkins":11,"people":null,"coords":[18.761569992962,99.000232088675],"weight":null},{"type":"Point","gid":119,"name":"Khun Nai Mae Kitchen","fsq_id":"5113308ce4b09a3b0dbbcb09","chkins":2,"people":null,"coords":[18.75893233945,99.015109979922],"weight":null},{"type":"Point","gid":121,"name":"Grandma Esan Hotdog","fsq_id":"4cce9e3cb571b60c813cdf65","chkins":2,"people":null,"coords":[18.798133210319,98.967508641703],"weight":null},{"type":"Point","gid":120,"name":"Memorize Buffet","fsq_id":"4c3c06087c1ee21e0e138c71","chkins":10,"people":null,"coords":[18.795975601451,98.965688474157],"weight":null},{"type":"Point","gid":125,"name":"Man Bamhee Keaw","fsq_id":"4bc9b5b10687ef3b494fdacc","chkins":10,"people":null,"coords":[18.786644526035,99.009537389384],"weight":null},{"type":"Point","gid":124,"name":"Natwat Home Cafe","fsq_id":"4f6330cee4b0ce431be58d6d","chkins":2,"people":null,"coords":[18.79952643549,99.004515228194],"weight":null},{"type":"Point","gid":123,"name":"Kao Soi Samer Jai","fsq_id":"4b6277f6f964a520c0482ae3","chkins":19,"people":null,"coords":[18.80469819661,99.005159965103],"weight":null},{"type":"Point","gid":127,"name":"Kanom Jean Sam Pha Koi Market","fsq_id":"4b92612ff964a52098f533e3","chkins":14,"people":null,"coords":[18.785616500777,99.008247915565],"weight":null},{"type":"Point","gid":129,"name":"Lung Thai","fsq_id":"4ce49c62e571a093bbea8587","chkins":1,"people":null,"coords":[18.789824939441,98.962267993853],"weight":null},{"type":"Point","gid":126,"name":"McDonald's","fsq_id":"4c29f29f3492a5932ba5b928","chkins":21,"people":null,"coords":[18.787222787485,98.993961902989],"weight":null},{"type":"Point","gid":128,"name":"The Volcano","fsq_id":"51bdbc86498e44f45c867177","chkins":37,"people":null,"coords":[18.792266428172,98.95500622024],"weight":null},{"type":"Point","gid":122,"name":"Samsen Villa","fsq_id":"4c53b21a728920a15c6c8281","chkins":6,"people":null,"coords":[18.794707881502,99.000443205607],"weight":null},{"type":"Point","gid":135,"name":"Mix","fsq_id":"4b63df19f964a52026952ae3","chkins":9,"people":null,"coords":[18.799494312253,98.969054698165],"weight":null},{"type":"Point","gid":140,"name":"Deck1","fsq_id":"4ce7cc26f3bda1433ce9b4e4","chkins":3,"people":null,"coords":[18.789664313941,99.004040158892],"weight":null},{"type":"Point","gid":138,"name":"Kao Tom Dang","fsq_id":"4b8bba97f964a520a8a832e3","chkins":4,"people":null,"coords":[18.788604181801,98.998712596007],"weight":null},{"type":"Point","gid":134,"name":"Kanom Jean Lom Kao","fsq_id":"4c04a62d39d476b00acc31a7","chkins":4,"people":null,"coords":[18.791752433486,98.951578934562],"weight":null},{"type":"Point","gid":133,"name":"Baan Din Pao","fsq_id":"4cc6786f806246886d39422f","chkins":0,"people":null,"coords":[18.792170054288,98.951273532868],"weight":null},{"type":"Point","gid":136,"name":"1 Baht Kao Tom","fsq_id":"4b98e0c0f964a520cd5335e3","chkins":4,"people":null,"coords":[18.787993799663,98.98724306572],"weight":null},{"type":"Point","gid":137,"name":"Yentafo Sa-ard","fsq_id":"4bdd07d1645e0f47c4b36a19","chkins":3,"people":null,"coords":[18.789664313941,98.986700129375],"weight":null},{"type":"Point","gid":132,"name":"Siphing Noodle","fsq_id":"4c3806313849c928e6e5beb1","chkins":8,"people":null,"coords":[18.789407312823,98.965593478966],"weight":null},{"type":"Point","gid":131,"name":"Chor Steak","fsq_id":"4c1c7de763750f4769b2b667","chkins":28,"people":null,"coords":[18.796281957641,98.976078937128],"weight":null},{"type":"Point","gid":130,"name":"Matsu Resturant","fsq_id":"51069881e4b0cc17d6471343","chkins":6,"people":null,"coords":[18.795029122726,98.982119103965],"weight":null},{"type":"Point","gid":141,"name":"Fah Thani Seafood","fsq_id":"4e92fee27ee629d9b48ad874","chkins":6,"people":null,"coords":[18.766725420123,98.982797774396],"weight":null},{"type":"Point","gid":143,"name":"KFC","fsq_id":"50e26d00e4b0a6d1d8844d9c","chkins":7,"people":null,"coords":[18.772219473149,98.998950130658],"weight":null},{"type":"Point","gid":142,"name":"Gut-Jung","fsq_id":"4ddce65d45ddaa53edb29244","chkins":15,"people":null,"coords":[18.75805023511,99.009333788255],"weight":null},{"type":"Point","gid":139,"name":"McDonald's","fsq_id":"4bc5209b6c26b713cefbeaf3","chkins":6,"people":null,"coords":[18.783656810251,99.000477139128],"weight":null},{"type":"Point","gid":144,"name":"Jia Tong Heng","fsq_id":"4b8a6a4ff964a520e86b32e3","chkins":15,"people":null,"coords":[18.781632843646,99.001359410689],"weight":null},{"type":"Point","gid":145,"name":"Yangzi Jiang","fsq_id":"4bdc19a23904a5936ed64c9e","chkins":4,"people":null,"coords":[18.798562735727,98.967595556738],"weight":null},{"type":"Point","gid":146,"name":"Double Floor Moo Jum","fsq_id":"4fa66fd5e4b0ddd496dfa85e","chkins":1,"people":null,"coords":[18.792876794824,98.953818546985],"weight":null},{"type":"Point","gid":149,"name":"P.P. Moo Jum","fsq_id":"4f92c796e4b061a42561ef52","chkins":9,"people":null,"coords":[18.789182436523,98.978556084201],"weight":null},{"type":"Point","gid":148,"name":"Inbox","fsq_id":"51691d53e4b00d7bee09f883","chkins":19,"people":null,"coords":[18.787929548783,98.962743063155],"weight":null},{"type":"Point","gid":147,"name":"Mayom Kitchen","fsq_id":"4be54b05cf200f470908133c","chkins":4,"people":null,"coords":[18.796153462181,98.969122565208],"weight":null},{"type":"Point","gid":153,"name":"Grandma Ship Noodle","fsq_id":"526a273e11d27d482cf0365e","chkins":6,"people":null,"coords":[18.78976068926,98.962675196112],"weight":null},{"type":"Point","gid":152,"name":"I Din Klin Krok","fsq_id":"518b8268498ee99b793f7b9f","chkins":5,"people":null,"coords":[18.79162393457,98.958195971266],"weight":null},{"type":"Point","gid":151,"name":"Nantharam Kao Man Kai","fsq_id":"51722389e4b05b6423fc34db","chkins":9,"people":null,"coords":[18.80884191535,98.954191815722],"weight":null},{"type":"Point","gid":154,"name":"Yui Phochana","fsq_id":"4d1ebcfd5acaa35d1082ba35","chkins":1,"people":null,"coords":[18.797358103265,99.008739951628],"weight":null},{"type":"Point","gid":176,"name":"Korat Grilled Chicken","fsq_id":"4cda7fc7c409b60c17fcce1a","chkins":5,"people":null,"coords":[18.846692788425,98.993300199319],"weight":null},{"type":"Point","gid":150,"name":"Masterday Fried Chicken","fsq_id":"4eeb2c88722eaa76d95c4d5a","chkins":2,"people":null,"coords":[18.808488578973,98.956804696882],"weight":null},{"type":"Point","gid":158,"name":"Hello Solao","fsq_id":"50bc3da3e4b01dc9b20fcb1b","chkins":6,"people":null,"coords":[18.766918196944,98.949542923269],"weight":null},{"type":"Point","gid":155,"name":"Oh Moon","fsq_id":"5016698de4b06bc0beabf178","chkins":0,"people":null,"coords":[18.796555010167,99.007857680067],"weight":null},{"type":"Point","gid":157,"name":"Sapao Kum","fsq_id":"51adde59498e30f40ac0da6f","chkins":3,"people":null,"coords":[18.749117541449,98.944232327145],"weight":null},{"type":"Point","gid":156,"name":"McDonald's","fsq_id":"52a5b7e611d251e44dc16205","chkins":12,"people":null,"coords":[18.765231392289,98.991637456762],"weight":null},{"type":"Point","gid":162,"name":"Terrace Behind Campus","fsq_id":"4d8978b176e1236a01220643","chkins":0,"people":null,"coords":[18.791832745259,98.953733713181],"weight":null},{"type":"Point","gid":161,"name":"Just Enough Kitchen","fsq_id":"4e246c35b61cdcf1ecdc079c","chkins":0,"people":null,"coords":[18.791736371127,98.955260721651],"weight":null},{"type":"Point","gid":160,"name":"Bai Tong Tung","fsq_id":"4fc4638ce4b00cc023f3180a","chkins":0,"people":null,"coords":[18.793246226196,98.952342438797],"weight":null},{"type":"Point","gid":159,"name":"Chutiporn Pad Thai","fsq_id":"4df4c15cd1649c8a28e763cc","chkins":1,"people":null,"coords":[18.791800620555,98.957432467031],"weight":null},{"type":"Point","gid":3,"name":"The Good View","fsq_id":"4b8288c8f964a52027d730e3","chkins":58,"people":null,"coords":[18.790413636351,99.003681015185],"weight":null},{"type":"Point","gid":4,"name":"The Riverside","fsq_id":"4b59b688f964a520359428e3","chkins":48,"people":null,"coords":[18.790255424925,99.004108095092],"weight":null},{"type":"Point","gid":164,"name":"Dada Kafe","fsq_id":"4c76192fff1fb60c771bf8a7","chkins":5,"people":null,"coords":[18.78540768238,98.992655462409],"weight":null},{"type":"Point","gid":163,"name":"Keaw Pla Sod","fsq_id":"4cadc151d1f8b60caa3f71c6","chkins":3,"people":null,"coords":[18.767384073352,98.969309199577],"weight":null},{"type":"Point","gid":175,"name":"Puu Jaa","fsq_id":"504b0e3ae4b0d1cf33765440","chkins":6,"people":null,"coords":[18.758965970146,99.047152698032],"weight":null},{"type":"Point","gid":174,"name":"Sabb Ver","fsq_id":"51d02941498e81b283c051c8","chkins":5,"people":null,"coords":[18.800136775819,99.018563706119],"weight":null},{"type":"Point","gid":177,"name":"Cafe DinDin","fsq_id":"51e00ac4498e6480eb01580f","chkins":13,"people":null,"coords":[18.826909263234,99.007246876679],"weight":null},{"type":"Point","gid":178,"name":"Noodle Recipe Station","fsq_id":"5141842be4b092a818fce717","chkins":16,"people":null,"coords":[18.808054937859,98.994929008353],"weight":null},{"type":"Point","gid":172,"name":"Unchan Noodle","fsq_id":"4fdc0a4be4b01d2338e829c4","chkins":22,"people":null,"coords":[18.798064822021,98.970666540439],"weight":null},{"type":"Point","gid":165,"name":"Tao Tarn Moo Kata","fsq_id":"4d2b05e2068e8cfaa7f9de4c","chkins":4,"people":null,"coords":[18.748378484466,98.945895069701],"weight":null},{"type":"Point","gid":171,"name":"Pun Pun Organic Vegetarian Restaurant","fsq_id":"4d995afc744f3704529b0558","chkins":64,"people":null,"coords":[18.787303101418,98.967748257585],"weight":null},{"type":"Point","gid":170,"name":"Hong Tauw Inn","fsq_id":"4d00f5a60457b1f7cd1a3478","chkins":5,"people":null,"coords":[18.799317634343,98.966865986024],"weight":null},{"type":"Point","gid":169,"name":"Ajiyoshi","fsq_id":"4dc29fd245ddd5b5b6b0445a","chkins":9,"people":null,"coords":[18.802369317641,98.965305044033],"weight":null},{"type":"Point","gid":168,"name":"Ninja Ramen","fsq_id":"4c25e321f7ced13a2f4f256d","chkins":3,"people":null,"coords":[18.798835784553,98.971311277349],"weight":null},{"type":"Point","gid":173,"name":"Great Teast","fsq_id":"4bf7c0868d30d13a1b76ff17","chkins":6,"people":null,"coords":[18.808054937859,99.003039120006],"weight":null},{"type":"Point","gid":166,"name":"Krua Ya","fsq_id":"4bdd21a1f219c9b682111210","chkins":3,"people":null,"coords":[18.765199262513,98.953021109229],"weight":null},{"type":"Point","gid":179,"name":"Lab Pa Dee Khom","fsq_id":"4ca3334aa73cb60c976d1678","chkins":3,"people":null,"coords":[18.809725253046,99.001919313795],"weight":null},{"type":"Point","gid":167,"name":"Sukoi Soi Lak","fsq_id":"4d5e5c72338bb60cd2580ebd","chkins":6,"people":null,"coords":[18.808633125762,98.957059198294],"weight":null},{"type":"Point","gid":181,"name":"Chang Phuek BBQ","fsq_id":"4c7f943a171b224b081911b1","chkins":4,"people":null,"coords":[18.796008904672,98.986751029658],"weight":null},{"type":"Point","gid":189,"name":"Jiaw Dao","fsq_id":"4cadec272303a143f370eaf0","chkins":3,"people":null,"coords":[18.793053479494,98.953564045573],"weight":null},{"type":"Point","gid":180,"name":"Chiw Lee Noodle","fsq_id":"4d1c17f5c50e6ea81712d0b8","chkins":0,"people":null,"coords":[18.823472601714,99.008773885149],"weight":null},{"type":"Point","gid":182,"name":"Bai Por Khao Tom","fsq_id":"4cf240d2e3b9a09348894353","chkins":3,"people":null,"coords":[18.736504929894,98.955464322781],"weight":null},{"type":"Point","gid":183,"name":"MK","fsq_id":"4baaf166f964a520d58e3ae3","chkins":12,"people":null,"coords":[18.742931856047,98.961029420316],"weight":null},{"type":"Point","gid":210,"name":"Miyabi","fsq_id":"52845c22498eec79ae2566b6","chkins":16,"people":null,"coords":[18.806191874444,99.017986836253],"weight":null},{"type":"Point","gid":209,"name":"Sukishi","fsq_id":"528471ad11d252e04c3fff09","chkins":19,"people":null,"coords":[18.808054937859,99.017409966386],"weight":null},{"type":"Point","gid":208,"name":"Wagaya","fsq_id":"5284664811d229f8876bf877","chkins":12,"people":null,"coords":[18.806384606088,99.017749301602],"weight":null},{"type":"Point","gid":207,"name":"KFC","fsq_id":"52904f5a11d22474d9bafbca","chkins":5,"people":null,"coords":[18.806288240287,99.018258304425],"weight":null},{"type":"Point","gid":225,"name":"Victory Monument Noodle","fsq_id":"522d5fec498e049273b2e4eb","chkins":6,"people":null,"coords":[18.799791451957,99.018275271186],"weight":null},{"type":"Point","gid":224,"name":"Khun Nai Mae Kitchen","fsq_id":"51d409ae498e009c26dc88a6","chkins":3,"people":null,"coords":[18.800080560355,99.018343138229],"weight":null},{"type":"Point","gid":223,"name":"Subway","fsq_id":"51fc1c77498e68f42e5a807d","chkins":9,"people":null,"coords":[18.800144806598,99.018843657672],"weight":null},{"type":"Point","gid":222,"name":"McDonald's","fsq_id":"5018c8d3e4b0d1cd67c48f80","chkins":30,"people":null,"coords":[18.800361637488,99.019199959648],"weight":null},{"type":"Point","gid":227,"name":"Miyabi","fsq_id":"520a258511d20ef0a45c91e6","chkins":7,"people":null,"coords":[18.765978407861,99.037642828616],"weight":null},{"type":"Point","gid":226,"name":"Fuji","fsq_id":"51e501d1498ebc95ee55de76","chkins":7,"people":null,"coords":[18.7652715545,99.037532544671],"weight":null},{"type":"Point","gid":221,"name":"Coco Salad","fsq_id":"4d6848826297721e5accb9b5","chkins":3,"people":null,"coords":[18.823593046647,99.011267998984],"weight":null},{"type":"Point","gid":220,"name":"McDonald's","fsq_id":"4d0ebc415b8a8cfa1315ec83","chkins":22,"people":null,"coords":[18.823986499494,99.011632784341],"weight":null},{"type":"Point","gid":219,"name":"Lum Lum","fsq_id":"4c81d61fd4e2370494316288","chkins":6,"people":null,"coords":[18.824203299648,99.01162430096],"weight":null},{"type":"Point","gid":1,"name":"The Meeting Room","fsq_id":"4ebb8c195c5c3157fdd36b99","chkins":0,"people":null,"coords":[18.791872690278,99.00240905981],"weight":null},{"type":"Point","gid":5,"name":"Huen Kha Jao","fsq_id":"4c56c1d0d12a20a18f1465bd","chkins":1,"people":null,"coords":[18.793239443181,99.007320478739],"weight":null},{"type":"Point","gid":6,"name":"Kitchen Hush","fsq_id":"4be03909fa629c74069725bc","chkins":4,"people":null,"coords":[18.792896657322,99.004646587148],"weight":null},{"type":"Point","gid":7,"name":"VT Nam Nueng","fsq_id":"4bc5c52269369521a6768488","chkins":20,"people":null,"coords":[18.785434299908,99.005259353971],"weight":null},{"type":"Point","gid":8,"name":"The Duke's","fsq_id":"4b8cce7ff964a520addd32e3","chkins":12,"people":null,"coords":[18.785188185904,99.005259353971],"weight":null},{"type":"Point","gid":9,"name":"Love at First Bite","fsq_id":"4b3dab30f964a520359625e3","chkins":18,"people":null,"coords":[18.78610232182,99.006735564953],"weight":null},{"type":"Point","gid":10,"name":"Khao Soi Islam","fsq_id":"4bb97426935e95211d2b2790","chkins":6,"people":null,"coords":[18.786779130792,99.001749871258],"weight":null},{"type":"Point","gid":11,"name":"Tubtim-krob J' Auan","fsq_id":"4d047375e350b60ca1948342","chkins":19,"people":null,"coords":[18.781364582873,99.001731302567],"weight":null},{"type":"Point","gid":12,"name":"Chang Moi Guay Jub","fsq_id":"4e1d0daed22dc55c99b94a3a","chkins":1,"people":null,"coords":[18.790189503453,98.99887172406],"weight":null},{"type":"Point","gid":13,"name":"Midnight Fried Chicken","fsq_id":"4b633439f964a520626a2ae3","chkins":19,"people":null,"coords":[18.780292200464,98.998221819854],"weight":null},{"type":"Point","gid":14,"name":"Toey Dimsum","fsq_id":"4d7f56b4f635236a132f7716","chkins":6,"people":null,"coords":[18.778077093879,98.996104989012],"weight":null},{"type":"Point","gid":15,"name":"Kiat Ocha","fsq_id":"4d0c2e935c46a093342807b4","chkins":20,"people":null,"coords":[18.789679709868,98.986393563304],"weight":null},{"type":"Point","gid":16,"name":"Three King Monument Guay Jub","fsq_id":"4bb947c953649c749feb47fb","chkins":4,"people":null,"coords":[18.790857506504,98.986597818912],"weight":null},{"type":"Point","gid":17,"name":"Miss Cornerry","fsq_id":"4d173bcd1356a093df9cda82","chkins":14,"people":null,"coords":[18.789802763633,98.984499556761],"weight":null},{"type":"Point","gid":18,"name":"Seasons Cafe","fsq_id":"5173c984e4b0e47c000ec808","chkins":6,"people":null,"coords":[18.788783172579,98.980117345543],"weight":null},{"type":"Point","gid":19,"name":"Tup Noi","fsq_id":"4c107f5681e976b071500feb","chkins":2,"people":null,"coords":[18.787640520096,98.979783109094],"weight":null},{"type":"Point","gid":20,"name":"Huen Phen","fsq_id":"4d0af49b109d6dcba8748c8d","chkins":23,"people":null,"coords":[18.785900157573,98.985205167041],"weight":null},{"type":"Point","gid":21,"name":"Ong Tipros","fsq_id":"4bddb30fe75c0f479c3dc503","chkins":12,"people":null,"coords":[18.794654526137,98.986727799753],"weight":null},{"type":"Point","gid":22,"name":"Kaen Chai Esarn Food","fsq_id":"4d1c41451cb9a143eb3aad2b","chkins":0,"people":null,"coords":[18.79338886244,98.982122764236],"weight":null},{"type":"Point","gid":23,"name":"Fern Forest Cafe","fsq_id":"4bc2a6e94cdfc9b6f9719621","chkins":7,"people":null,"coords":[18.793845908761,98.982494138068],"weight":null},{"type":"Point","gid":24,"name":"Coca Suki","fsq_id":"4ba4bc84f964a52067b038e3","chkins":7,"people":null,"coords":[18.796025651071,98.985613678257],"weight":null},{"type":"Point","gid":25,"name":"Kha Moo Chang Phueak","fsq_id":"4bc5af7d4a9aa593f6bc067b","chkins":7,"people":null,"coords":[18.796060807973,98.985985052089],"weight":null},{"type":"Point","gid":26,"name":"Hoi Kha","fsq_id":"4c961de858d4b60c09073829","chkins":0,"people":null,"coords":[18.784388312908,98.982085626852],"weight":null},{"type":"Point","gid":27,"name":"Tanya","fsq_id":"4c105815ce57c92891d681d2","chkins":5,"people":null,"coords":[18.790681716485,98.989290279194],"weight":null},{"type":"Point","gid":28,"name":"W by Wanlamun","fsq_id":"4b596878f964a520738728e3","chkins":4,"people":null,"coords":[18.789416022926,98.996123557703],"weight":null},{"type":"Point","gid":29,"name":"Blue Diamond","fsq_id":"4c1c55e9b306c92830d263b7","chkins":6,"people":null,"coords":[18.793951380813,98.99122142312],"weight":null},{"type":"Point","gid":30,"name":"Jok Sompet","fsq_id":"4b6777fcf964a520d9502be3","chkins":16,"people":null,"coords":[18.795006097697,98.989810202559],"weight":null},{"type":"Point","gid":31,"name":"Mont Blanc","fsq_id":"4b5aac46f964a52044d028e3","chkins":16,"people":null,"coords":[18.797554969542,98.966655044131],"weight":null},{"type":"Point","gid":32,"name":"Mont Nom Sod","fsq_id":"4c99eefad4b1b1f7577acb35","chkins":51,"people":null,"coords":[18.797326451582,98.966562200673],"weight":null},{"type":"Point","gid":33,"name":"Solao Somtum","fsq_id":"4e7f0c76b63474966605debc","chkins":22,"people":null,"coords":[18.797361608213,98.971055824041],"weight":null},{"type":"Point","gid":34,"name":"Tong Tem Toh","fsq_id":"4cbf2e65575d236a405bbd8e","chkins":53,"people":null,"coords":[18.796236592377,98.967416360487],"weight":null},{"type":"Point","gid":184,"name":"Khaomao-Khaofang","fsq_id":"4eba46970cd6f29a6cf2c120","chkins":8,"people":null,"coords":[18.730013486262,98.943723324321],"weight":null},{"type":"Point","gid":185,"name":"The Windmill","fsq_id":"4db037bbfa8ca4b3e9de01f3","chkins":11,"people":null,"coords":[18.747269892925,98.947863213952],"weight":null},{"type":"Point","gid":186,"name":"Im Plaphao","fsq_id":"4b6817e4f964a520f0662be3","chkins":12,"people":null,"coords":[18.748715880447,98.940499639773],"weight":null},{"type":"Point","gid":188,"name":"Bali House","fsq_id":"4f12c7ece4b06784122535d5","chkins":0,"people":null,"coords":[18.776540693149,98.953733713181],"weight":null},{"type":"Point","gid":187,"name":"Lab Lung Noi","fsq_id":"4db6b03ef7b121c29f77030b","chkins":0,"people":null,"coords":[18.772299794234,98.946268338438],"weight":null},{"type":"Point","gid":193,"name":"Pai Fha Noodle","fsq_id":"4e3790de52b1aec57ffb348f","chkins":1,"people":null,"coords":[18.774613025052,98.94630227196],"weight":null},{"type":"Point","gid":192,"name":"Khun Ning Noodle","fsq_id":"4bd9159c2e6f0f47a2c00908","chkins":2,"people":null,"coords":[18.774741536944,98.947863213952],"weight":null},{"type":"Point","gid":191,"name":"Kum Viang Yong","fsq_id":"4b7e8215f964a52016f02fe3","chkins":2,"people":null,"coords":[18.771078909616,98.949763491159],"weight":null},{"type":"Point","gid":196,"name":"MK","fsq_id":"4b602a54f964a52022d829e3","chkins":4,"people":null,"coords":[18.798353933385,99.022584828424],"weight":null},{"type":"Point","gid":199,"name":"Huen Soontaree Vechanont","fsq_id":"4d04c09ca26854813695b9bd","chkins":10,"people":null,"coords":[18.831309372112,98.993469866926],"weight":null},{"type":"Point","gid":198,"name":"The Garden Restaurant","fsq_id":"4b6a5a4ef964a5202cd32be3","chkins":9,"people":null,"coords":[18.819618318284,99.020616684173],"weight":null},{"type":"Point","gid":197,"name":"Ouan Ocha","fsq_id":"4bc555e2ccbcef3bbf76e6d2","chkins":3,"people":null,"coords":[18.774645153034,99.001206709842],"weight":null},{"type":"Point","gid":190,"name":"Mr. Chan & Miss Pauline","fsq_id":"4b3de969f964a5205b9725e3","chkins":9,"people":null,"coords":[18.736954822685,98.930760719086],"weight":null},{"type":"Point","gid":195,"name":"Dumrong","fsq_id":"4cd3a5309828b60cb2bad684","chkins":5,"people":null,"coords":[18.790322877516,99.000528039411],"weight":null},{"type":"Point","gid":194,"name":"Fuji","fsq_id":"52e0bfa411d205779d639b35","chkins":10,"people":null,"coords":[18.802305072247,98.967001720111],"weight":null},{"type":"Point","gid":201,"name":"Sizzler","fsq_id":"4bdfda776198c9b6178818ff","chkins":3,"people":null,"coords":[18.796571072066,98.975620834586],"weight":null},{"type":"Point","gid":200,"name":"KFC","fsq_id":"4bb48bd3a187ef3be3b84942","chkins":3,"people":null,"coords":[18.796667443431,98.975739601912],"weight":null},{"type":"Point","gid":206,"name":"Daidomon","fsq_id":"4d0c5023903d3704f6c7bc55","chkins":3,"people":null,"coords":[18.768878082108,98.976197704453],"weight":null},{"type":"Point","gid":205,"name":"Oishi Buffet","fsq_id":"4d19d66d6c8b5481b169fbcc","chkins":14,"people":null,"coords":[18.769006598384,98.974704629504],"weight":null},{"type":"Point","gid":204,"name":"Fuji","fsq_id":"4cb15155ef1b370489c74200","chkins":20,"people":null,"coords":[18.7693600176,98.975162732045],"weight":null},{"type":"Point","gid":203,"name":"Santafe","fsq_id":"50bc41ede4b060d019bbefe5","chkins":9,"people":null,"coords":[18.769536726933,98.975552967543],"weight":null},{"type":"Point","gid":202,"name":"MK","fsq_id":"4cac5bb4f47ea1432b3f9021","chkins":4,"people":null,"coords":[18.769440340047,98.975739601912],"weight":null},{"type":"Point","gid":215,"name":"Saboten","fsq_id":"528481fb498e349b8556f6de","chkins":4,"people":null,"coords":[18.807830086471,99.017749301602],"weight":null},{"type":"Point","gid":218,"name":"Sizzler","fsq_id":"52847c5a11d21abd44ab65ed","chkins":13,"people":null,"coords":[18.806641581274,99.017511766951],"weight":null},{"type":"Point","gid":217,"name":"Santafe","fsq_id":"52848f2811d24bf0d277769c","chkins":23,"people":null,"coords":[18.807251895808,99.01791896921],"weight":null},{"type":"Point","gid":216,"name":"Chabuton","fsq_id":"5284718911d28cd2fac4bd0b","chkins":9,"people":null,"coords":[18.807573113089,99.018054703296],"weight":null},{"type":"Point","gid":214,"name":"I Din Klin Krok","fsq_id":"52873c42498e5db997f6bfab","chkins":9,"people":null,"coords":[18.806770068738,99.018088636817],"weight":null},{"type":"Point","gid":213,"name":"Yoshinoya","fsq_id":"52845bf4498edc646c7acdf3","chkins":4,"people":null,"coords":[18.807476747969,99.017443899908],"weight":null},{"type":"Point","gid":212,"name":"Ootoya","fsq_id":"52846968498eace34564e76d","chkins":6,"people":null,"coords":[18.806994921542,99.017477833429],"weight":null},{"type":"Point","gid":211,"name":"Miyazaki","fsq_id":"5284e27d11d20f8c46e0e83d","chkins":10,"people":null,"coords":[18.808183424232,99.017851102166],"weight":null}]